featurestoresdk/__init__.py
featurestoresdk/feature_store_sdk.py
featurestoresdk/sdk_exception.py
featurestoresdk/singleton_manager.py
featurestoresdk/config/config.json
featurestoresdk_subhash-0.4.dist-info/licenses/LICENSES.txt
featurestoresdk_subhash-0.4.dist-info/METADATA
featurestoresdk_subhash-0.4.dist-info/WHEEL
featurestoresdk_subhash-0.4.dist-info/top_level.txt
featurestoresdk_subhash-0.4.dist-info/RECORD
