Metadata-Version: 2.4
Name: featurestoresdk_subhash
Version: 0.4
Summary: feature store SDK for Training Host
Home-page: https://gerrit.o-ran-sc.org/r/admin/repos/aiml-fw/athp/sdk/feature-store,general
Author: Joseph Thaliath
Author-email: jo.thaliath@samsung.com
License: Apache 2.0
License-File: LICENSES.txt
Dynamic: author
Dynamic: author-email
Dynamic: home-page
Dynamic: license
Dynamic: license-file
Dynamic: summary
